{
  "1529": {
    "code": "1529",
    "name": "樂事綠能科技股份有限公司",
    "close": 24.95,
    "change": 2.25,
    "changePct": "9.91",
    "volume": 1975795,
    "type": "漲停"
  },
  "1802": {
    "code": "1802",
    "name": "台灣玻璃工業股份有限公司",
    "close": 47.05,
    "change": 4.25,
    "changePct": "9.93",
    "volume": 93106758,
    "type": "漲停"
  },
  "1815": {
    "code": "1815",
    "name": "富喬工業股份有限公司",
    "close": 96.6,
    "change": 8.7,
    "changePct": "9.90",
    "volume": 80270121,
    "type": "漲停"
  },
  "2337": {
    "code": "2337",
    "name": "旺宏電子股份有限公司",
    "close": 98.5,
    "change": 8.9,
    "changePct": "9.93",
    "volume": 347913513,
    "type": "漲停"
  },
  "2438": {
    "code": "2438",
    "name": "翔耀實業股份有限公司",
    "close": 22.8,
    "change": 2.05,
    "changePct": "9.88",
    "volume": 510743,
    "type": "漲停"
  },
  "3252": {
    "code": "3252",
    "name": "海灣國際開發(股)公司",
    "close": 20.15,
    "change": 1.8,
    "changePct": "9.81",
    "volume": 312305,
    "type": "漲停"
  },
  "3529": {
    "code": "3529",
    "name": "力旺電子股份有限公司",
    "close": 1985.0,
    "change": 180.0,
    "changePct": "9.97",
    "volume": 2245239,
    "type": "漲停"
  },
  "3555": {
    "code": "3555",
    "name": "博士旺創新股份有限公司",
    "close": 121.0,
    "change": 11.0,
    "changePct": "10.00",
    "volume": 448433,
    "type": "漲停"
  },
  "3581": {
    "code": "3581",
    "name": "博磊科技股份有限公司",
    "close": 72.2,
    "change": 6.5,
    "changePct": "9.89",
    "volume": 1773376,
    "type": "漲停"
  },
  "4523": {
    "code": "4523",
    "name": "永彰科技股份有限公司",
    "close": 31.35,
    "change": 2.85,
    "changePct": "10.00",
    "volume": 614678,
    "type": "漲停"
  },
  "4806": {
    "code": "4806",
    "name": "桂田文創娛樂股份有限公司",
    "close": 11.7,
    "change": 1.05,
    "changePct": "9.86",
    "volume": 100940,
    "type": "漲停"
  },
  "4908": {
    "code": "4908",
    "name": "前鼎光電股份有限公司",
    "close": 79.2,
    "change": 7.2,
    "changePct": "10.00",
    "volume": 2909418,
    "type": "漲停"
  },
  "4989": {
    "code": "4989",
    "name": "李長榮科技股份有限公司",
    "close": 50.2,
    "change": 4.55,
    "changePct": "9.97",
    "volume": 8191121,
    "type": "漲停"
  },
  "5386": {
    "code": "5386",
    "name": "青雲國際科技股份有限公司",
    "close": 159.5,
    "change": 14.5,
    "changePct": "10.00",
    "volume": 1961292,
    "type": "漲停"
  },
  "5475": {
    "code": "5475",
    "name": "德宏工業股份有限公司",
    "close": 163.0,
    "change": 14.5,
    "changePct": "9.76",
    "volume": 5533632,
    "type": "漲停"
  },
  "6291": {
    "code": "6291",
    "name": "沛亨半導體股份有限公司",
    "close": 276.5,
    "change": 25.0,
    "changePct": "9.94",
    "volume": 3984995,
    "type": "漲停"
  },
  "6509": {
    "code": "6509",
    "name": "聚和國際股份有限公司",
    "close": 37.7,
    "change": 3.4,
    "changePct": "9.91",
    "volume": 5001170,
    "type": "漲停"
  },
  "6588": {
    "code": "6588",
    "name": "東典光電科技股份有限公司",
    "close": 92.6,
    "change": 8.4,
    "changePct": "9.98",
    "volume": 1940627,
    "type": "漲停"
  },
  "6683": {
    "code": "6683",
    "name": "雍智科技股份有限公司",
    "close": 790.0,
    "change": 71.0,
    "changePct": "9.87",
    "volume": 342525,
    "type": "漲停"
  },
  "6716": {
    "code": "6716",
    "name": "應廣科技股份有限公司",
    "close": 73.2,
    "change": 6.6,
    "changePct": "9.91",
    "volume": 2201299,
    "type": "漲停"
  },
  "6861": {
    "code": "6861",
    "name": "睿生光電股份有限公司",
    "close": 78.4,
    "change": 7.1,
    "changePct": "9.96",
    "volume": 2603528,
    "type": "漲停"
  },
  "6907": {
    "code": "6907",
    "name": "雅特力科技(開曼)股份有限公司",
    "close": 58.7,
    "change": 5.3,
    "changePct": "9.93",
    "volume": 1449436,
    "type": "漲停"
  },
  "6924": {
    "code": "6924",
    "name": "榮惠集團(開曼)股份有限公司",
    "close": 62.5,
    "change": 5.6,
    "changePct": "9.84",
    "volume": 31006,
    "type": "漲停"
  },
  "7740": {
    "code": "7740",
    "name": "熙特爾新能源股份有限公司",
    "close": 160.0,
    "change": 14.5,
    "changePct": "9.97",
    "volume": 358809,
    "type": "漲停"
  },
  "8087": {
    "code": "8087",
    "name": "麗升能源科技股份有限公司",
    "close": 27.8,
    "change": 2.5,
    "changePct": "9.88",
    "volume": 61395,
    "type": "漲停"
  },
  "8472": {
    "code": "8472",
    "name": "夠麻吉股份有限公司",
    "close": 60.8,
    "change": 5.5,
    "changePct": "9.95",
    "volume": 57217,
    "type": "漲停"
  }
}